{
    "name": "Dough Shaper Tool",
    "functional_purpose": "to shape the cubic dough into a calabash-like shape",
    "construction_steps": [
        {
            "step_id": 0,
            "Instruction": "Add a cylindrical body",
            "reason": "this will serve as the base to shape the dough",
            "is_graspable": false
        },
        {
            "step_id": 1,
            "Instruction": "Add a conical extension at the top",
            "reason": "this will allow the tool to scoop and shape the dough into a calabash-like shape",
            "is_graspable": false
        },
        {
            "step_id": 2,
            "Instruction": "Add a cylindrical handle at the bottom",
            "reason": "this will allow the robot to hold and manipulate the tool",
            "is_graspable": true
        }
    ],
    "simulation_properties": {
        "density": 500.0,
        "friction": 0.5,
        "restitution": 0.1,
        "is_graspable_default": true
    },
    "placement_func": "def placement():\n    self.tool = scene.add_entity(\n        gs.Morph.Mesh(\n            filename=\"assembled_tool.stl\",\n            pos=(0.0, 0.0, 0.0),\n            euler=(0, 0, 0),\n            scale=(1, 1, 1),\n        )\n    )"
}